alertify/__init__.py
alertify/exception/__init__.py
alertify/exception/api_error.py
alertify/opsgenie/__init__.py
alertify/opsgenie/client.py
alertify/pagerduty/__init__.py
alertify/pagerduty/client.py
alertify/sendgrid/__init__.py
alertify/sendgrid/client.py
alertify/slack/__init__.py
alertify/slack/client.py
alertify/util/__init__.py
alertify/util/file_system.py
alertify/webhook/__init__.py
alertify/webhook/client.py
alertify-0.8.0.dist-info/LICENSE.txt
alertify-0.8.0.dist-info/METADATA
alertify-0.8.0.dist-info/WHEEL
alertify-0.8.0.dist-info/top_level.txt
alertify-0.8.0.dist-info/RECORD
