Metadata-Version: 2.1
Name: alertify
Version: 0.8.0
Summary: Uptimedog Alerting Integrations.
Home-page: https://github.com/uptimedog/alertify/
Author: Clivern
Author-email: hello@clivern.com
License: MIT
Project-URL: Documentation, https://github.com/uptimedog/alertify/
Project-URL: Source, https://github.com/uptimedog/alertify/
Project-URL: Changelog, https://github.com/uptimedog/alertify/blob/main/CHANGELOG.rst
Project-URL: Tracker, https://github.com/uptimedog/alertify/issues
Project-URL: Download, https://pypi.org/project/alertify/#files
Platform: any
Classifier: Development Status :: 5 - Production/Stable
Classifier: Programming Language :: Python
Classifier: License :: OSI Approved :: MIT License
License-File: LICENSE.txt
Requires-Dist: requests
Requires-Dist: importlib-metadata ; python_version < "3.8"
